llama_distributed/__init__.py
llama_distributed/config.py
llama_distributed/core.py
llama_distributed/package.py
llama_distributed-0.1.0.dist-info/METADATA
llama_distributed-0.1.0.dist-info/WHEEL
llama_distributed-0.1.0.dist-info/licenses/LICENSE
llama_distributed-0.1.0.dist-info/RECORD
