Metadata-Version: 2.4
Name: llama-distributed
Version: 0.1.0
Summary: Distributed task execution and coordination for LlamaAI workloads.
Project-URL: Homepage, https://github.com/yourusername/llama-distributed
Project-URL: Bug Tracker, https://github.com/yourusername/llama-distributed/issues
Project-URL: Documentation, https://yourusername.github.io/llama-distributed/
Author-email: Your Name <your.email@example.com>
License: MIT License
License-File: LICENSE
Classifier: Development Status :: 3 - Alpha
Classifier: Intended Audience :: Developers
Classifier: License :: OSI Approved :: MIT License
Classifier: Programming Language :: Python :: 3
Classifier: Programming Language :: Python :: 3.8
Classifier: Programming Language :: Python :: 3.9
Classifier: Programming Language :: Python :: 3.10
Classifier: Programming Language :: Python :: 3.11
Classifier: Topic :: Software Development :: Libraries :: Python Modules
Classifier: Topic :: System :: Distributed Computing
Requires-Python: >=3.8
Requires-Dist: celery[redis]>=5.3.0
Requires-Dist: loguru>=0.7.0
Requires-Dist: pydantic>=1.10.0
Provides-Extra: all
Requires-Dist: black>=23.3.0; extra == 'all'
Requires-Dist: dask[distributed]>=2023.3.0; extra == 'all'
Requires-Dist: isort>=5.12.0; extra == 'all'
Requires-Dist: mkdocs-material>=9.1.6; extra == 'all'
Requires-Dist: mkdocs>=1.4.2; extra == 'all'
Requires-Dist: mkdocstrings[python]>=0.20.0; extra == 'all'
Requires-Dist: mypy>=1.2.0; extra == 'all'
Requires-Dist: pre-commit>=3.3.1; extra == 'all'
Requires-Dist: pytest-celery>=0.0.0; extra == 'all'
Requires-Dist: pytest-cov>=4.1.0; extra == 'all'
Requires-Dist: pytest-mock>=3.10.0; extra == 'all'
Requires-Dist: pytest>=7.3.1; extra == 'all'
Requires-Dist: ray[default]>=2.4.0; extra == 'all'
Requires-Dist: redis; extra == 'all'
Requires-Dist: ruff>=0.0.260; extra == 'all'
Provides-Extra: dask
Requires-Dist: dask[distributed]>=2023.3.0; extra == 'dask'
Provides-Extra: dev
Requires-Dist: black>=23.3.0; extra == 'dev'
Requires-Dist: isort>=5.12.0; extra == 'dev'
Requires-Dist: mypy>=1.2.0; extra == 'dev'
Requires-Dist: pre-commit>=3.3.1; extra == 'dev'
Requires-Dist: pytest-celery>=0.0.0; extra == 'dev'
Requires-Dist: pytest-cov>=4.1.0; extra == 'dev'
Requires-Dist: pytest-mock>=3.10.0; extra == 'dev'
Requires-Dist: pytest>=7.3.1; extra == 'dev'
Requires-Dist: redis; extra == 'dev'
Requires-Dist: ruff>=0.0.260; extra == 'dev'
Provides-Extra: docs
Requires-Dist: mkdocs-material>=9.1.6; extra == 'docs'
Requires-Dist: mkdocs>=1.4.2; extra == 'docs'
Requires-Dist: mkdocstrings[python]>=0.20.0; extra == 'docs'
Provides-Extra: ray
Requires-Dist: ray[default]>=2.4.0; extra == 'ray'
